oira.statistics.deployment-1.1.2-py3.11-nspkg.pth
oira/statistics/deployment/__init__.py
oira/statistics/deployment/config.py
oira/statistics/deployment/content.py
oira/statistics/deployment/initializer.py
oira/statistics/deployment/metabase.py
oira/statistics/deployment/model.py
oira/statistics/deployment/scripts.py
oira/statistics/deployment/resources/intro_text.md
oira/statistics/deployment/tests/__init__.py
oira/statistics/deployment/tests/acceptance/login.robot
oira/statistics/deployment/upgrade/utils.py
oira/statistics/deployment/upgrade/alembic/README
oira/statistics/deployment/upgrade/alembic/env.py
oira/statistics/deployment/upgrade/alembic/script.py.mako
oira/statistics/deployment/upgrade/alembic/versions/20220921134624_.py
oira/statistics/deployment/upgrade/alembic/versions/20230228134447_add_newsletter_statistics_table.py
oira_statistics_deployment-1.1.2.dist-info/METADATA
oira_statistics_deployment-1.1.2.dist-info/WHEEL
oira_statistics_deployment-1.1.2.dist-info/entry_points.txt
oira_statistics_deployment-1.1.2.dist-info/namespace_packages.txt
oira_statistics_deployment-1.1.2.dist-info/top_level.txt
oira_statistics_deployment-1.1.2.dist-info/RECORD
