Metadata-Version: 2.4
Name: oira.statistics.deployment
Version: 1.1.2
Summary: Deployment helpers for the statistics of the OSHA-OiRA site.
Home-page: http://www.oiraproject.eu/
Author: syslab.com
Author-email: info@syslab.com
License: GPL
Keywords: euphorie osha oira
Classifier: Development Status :: 5 - Production/Stable
Classifier: License :: OSI Approved :: GNU General Public License (GPL)
Classifier: Programming Language :: Python :: 3 :: Only
Classifier: Programming Language :: Python :: 3.7
Classifier: Topic :: Software Development :: Libraries :: Python Modules
Requires-Python: ~= 3.8
Requires-Dist: alembic
Requires-Dist: metabase-api
Requires-Dist: setuptools
Requires-Dist: SQLAlchemy[postgresql]>=1.2.999999
Dynamic: author
Dynamic: author-email
Dynamic: classifier
Dynamic: description
Dynamic: description-content-type
Dynamic: home-page
Dynamic: keywords
Dynamic: license
Dynamic: requires-dist
Dynamic: requires-python
Dynamic: summary
